pyenvparser/__init__.py
pyenvparser/environment.py
pyenvparser-0.0.2.dist-info/METADATA
pyenvparser-0.0.2.dist-info/WHEEL
pyenvparser-0.0.2.dist-info/top_level.txt
pyenvparser-0.0.2.dist-info/RECORD
