Metadata-Version: 2.1
Name: pyenvparser
Version: 0.0.2
Summary: A package that parses configuration values.
Home-page: UNKNOWN
Author: jspenc72
Author-email: jspenc72@gmail.com
License: MIT
Keywords: env
Platform: UNKNOWN
Classifier: Development Status :: 3 - Alpha
Classifier: Intended Audience :: Developers
Classifier: License :: OSI Approved :: MIT License
Classifier: Programming Language :: Python :: 3
